napari_noise2vst/__init__.py
napari_noise2vst/_version.py
napari_noise2vst/_widget.py
napari_noise2vst/napari.yaml
napari_noise2vst/_tests/__init__.py
napari_noise2vst/_tests/test_widget.py
napari_noise2vst/pretrained_weights/__init__.py
napari_noise2vst/pretrained_weights/download.py
napari_noise2vst-0.1.1.dist-info/licenses/LICENSE
napari_noise2vst-0.1.1.dist-info/METADATA
napari_noise2vst-0.1.1.dist-info/WHEEL
napari_noise2vst-0.1.1.dist-info/entry_points.txt
napari_noise2vst-0.1.1.dist-info/top_level.txt
napari_noise2vst-0.1.1.dist-info/RECORD
