Metadata-Version: 2.4
Name: napari-noise2vst
Version: 0.1.1
Summary: A plugin for denoising microscopy images using Noise2VST
Author-email: Ibrahima Alain Gueye <gueyeibrahimaalain@gmail.com>
License: 
Project-URL: Bug Tracker, https://github.com/IbrahimaAlain/napari-noise2vst/issues
Project-URL: Documentation, https://github.com/IbrahimaAlain/napari-noise2vst
Project-URL: Source Code, https://github.com/IbrahimaAlain/napari-noise2vst
Project-URL: User Support, https://github.com/IbrahimaAlain/napari-noise2vst/issues
Classifier: Development Status :: 4 - Beta
Classifier: Framework :: napari
Classifier: Intended Audience :: Developers
Classifier: License :: OSI Approved :: MIT License
Classifier: Operating System :: OS Independent
Classifier: Programming Language :: Python
Classifier: Programming Language :: Python :: 3
Classifier: Programming Language :: Python :: 3 :: Only
Classifier: Programming Language :: Python :: 3.10
Classifier: Programming Language :: Python :: 3.11
Classifier: Programming Language :: Python :: 3.12
Classifier: Programming Language :: Python :: 3.13
Classifier: Topic :: Scientific/Engineering :: Image Processing
Requires-Python: >=3.10
License-File: LICENSE
Requires-Dist: numpy
Requires-Dist: matplotlib
Requires-Dist: torch
Requires-Dist: magicgui
Requires-Dist: qtpy
Requires-Dist: scikit-image
Requires-Dist: napari
Requires-Dist: torchvision
Requires-Dist: Noise2VST
Provides-Extra: all
Requires-Dist: napari[all]; extra == "all"
Provides-Extra: testing
Requires-Dist: tox; extra == "testing"
Requires-Dist: pytest; extra == "testing"
Requires-Dist: pytest-cov; extra == "testing"
Requires-Dist: pytest-qt; extra == "testing"
Requires-Dist: napari[qt]; extra == "testing"
Dynamic: license-file
